video_diffusion_pytorch/__init__.py
video_diffusion_pytorch/text.py
video_diffusion_pytorch/video_diffusion_pytorch.py
video_diffusion_pytorch-0.7.0.dist-info/LICENSE
video_diffusion_pytorch-0.7.0.dist-info/METADATA
video_diffusion_pytorch-0.7.0.dist-info/WHEEL
video_diffusion_pytorch-0.7.0.dist-info/top_level.txt
video_diffusion_pytorch-0.7.0.dist-info/RECORD
