Metadata-Version: 2.1
Name: video-diffusion-pytorch
Version: 0.7.0
Summary: Video Diffusion - Pytorch
Home-page: https://github.com/lucidrains/video-diffusion-pytorch
Author: Phil Wang
Author-email: lucidrains@gmail.com
License: MIT
Keywords: artificial intelligence,deep learning,denoising diffusion probabilistic models,video generation
Classifier: Development Status :: 4 - Beta
Classifier: Intended Audience :: Developers
Classifier: Topic :: Scientific/Engineering :: Artificial Intelligence
Classifier: License :: OSI Approved :: MIT License
Classifier: Programming Language :: Python :: 3.6
License-File: LICENSE
Requires-Dist: einops >=0.4
Requires-Dist: einops-exts
Requires-Dist: rotary-embedding-torch
Requires-Dist: sacremoses
Requires-Dist: sentencepiece
Requires-Dist: torch >=1.10
Requires-Dist: torchvision
Requires-Dist: transformers[torch]
Requires-Dist: tqdm
